{"expireTime":9007200811184863000,"key":"transformer-remark-markdown-html-ast-7ae51fe502759e43cb1f3bde47685532-gatsby-remark-imagesgatsby-remark-responsive-iframegatsby-remark-prismjsgatsby-remark-copy-linked-filesgatsby-remark-smartypants-","val":{"type":"root","children":[{"type":"element","tagName":"h2","properties":{},"children":[{"type":"text","value":"19. Running Your Application","position":{"start":{"line":1,"column":4,"offset":3},"end":{"line":1,"column":32,"offset":31}}}],"position":{"start":{"line":1,"column":1,"offset":0},"end":{"line":1,"column":32,"offset":31}}},{"type":"text","value":"\n"},{"type":"element","tagName":"p","properties":{},"children":[{"type":"text","value":"One of the biggest advantages of packaging your application as a jar and using an embedded HTTP server is that you can run your application as you would any other. Debugging Spring Boot applications is also easy. You do not need any special IDE plugins or extensions.","position":{"start":{"line":3,"column":1,"offset":33},"end":{"line":3,"column":268,"offset":300}}}],"position":{"start":{"line":3,"column":1,"offset":33},"end":{"line":3,"column":268,"offset":300}}},{"type":"text","value":"\n"},{"type":"element","tagName":"table","properties":{},"children":[{"type":"text","value":"\n"},{"type":"element","tagName":"thead","properties":{},"children":[{"type":"text","value":"\n"},{"type":"element","tagName":"tr","properties":{},"children":[{"type":"text","value":"\n"},{"type":"element","tagName":"th","properties":{"align":null},"children":[{"type":"element","tagName":"img","properties":{"src":"https://docs.spring.io/spring-boot/docs/current/reference/html/images/note.png","alt":"[Note]"},"children":[],"position":{"start":{"line":5,"column":3,"offset":304},"end":{"line":5,"column":92,"offset":393}}}],"position":{"start":{"line":5,"column":3,"offset":304},"end":{"line":5,"column":92,"offset":393}}},{"type":"text","value":"\n"}],"position":{"start":{"line":5,"column":1,"offset":302},"end":{"line":5,"column":94,"offset":395}}},{"type":"text","value":"\n"}],"position":{"start":{"line":5,"column":1,"offset":302},"end":{"line":5,"column":94,"offset":395}}},{"type":"text","value":"\n"},{"type":"element","tagName":"tbody","properties":{},"children":[{"type":"text","value":"\n"},{"type":"element","tagName":"tr","properties":{},"children":[{"type":"text","value":"\n"},{"type":"element","tagName":"td","properties":{"align":null},"children":[{"type":"text","value":"This section only covers jar based packaging. If you choose to package your application as a war file, you should refer to your server and IDE documentation.","position":{"start":{"line":7,"column":3,"offset":463},"end":{"line":7,"column":160,"offset":620}}}],"position":{"start":{"line":7,"column":3,"offset":463},"end":{"line":7,"column":160,"offset":620}}},{"type":"text","value":"\n"}],"position":{"start":{"line":7,"column":1,"offset":461},"end":{"line":7,"column":162,"offset":622}}},{"type":"text","value":"\n"}],"position":{"start":{"line":7,"column":1,"offset":461},"end":{"line":7,"column":162,"offset":622}}},{"type":"text","value":"\n"}],"position":{"start":{"line":5,"column":1,"offset":302},"end":{"line":7,"column":162,"offset":622}}},{"type":"text","value":"\n"},{"type":"element","tagName":"h2","properties":{},"children":[{"type":"text","value":"19.1 Running from an IDE","position":{"start":{"line":9,"column":4,"offset":627},"end":{"line":9,"column":28,"offset":651}}}],"position":{"start":{"line":9,"column":1,"offset":624},"end":{"line":9,"column":28,"offset":651}}},{"type":"text","value":"\n"},{"type":"element","tagName":"p","properties":{},"children":[{"type":"text","value":"You can run a Spring Boot application from your IDE as a simple Java application. However, you first need to import your project. Import steps vary depending on your IDE and build system. Most IDEs can import Maven projects directly. For example, Eclipse users can select ","position":{"start":{"line":11,"column":1,"offset":653},"end":{"line":11,"column":273,"offset":925}}},{"type":"raw","value":"<code class=\"language-text\">Import…</code>","position":{"start":{"line":11,"column":273,"offset":925},"end":{"line":11,"column":282,"offset":934}}},{"type":"text","value":" → ","position":{"start":{"line":11,"column":282,"offset":934},"end":{"line":11,"column":285,"offset":937}}},{"type":"raw","value":"<code class=\"language-text\">Existing Maven Projects</code>","position":{"start":{"line":11,"column":285,"offset":937},"end":{"line":11,"column":310,"offset":962}}},{"type":"text","value":" from the ","position":{"start":{"line":11,"column":310,"offset":962},"end":{"line":11,"column":320,"offset":972}}},{"type":"raw","value":"<code class=\"language-text\">File</code>","position":{"start":{"line":11,"column":320,"offset":972},"end":{"line":11,"column":326,"offset":978}}},{"type":"text","value":"menu.","position":{"start":{"line":11,"column":326,"offset":978},"end":{"line":11,"column":331,"offset":983}}}],"position":{"start":{"line":11,"column":1,"offset":653},"end":{"line":11,"column":331,"offset":983}}},{"type":"text","value":"\n"},{"type":"element","tagName":"p","properties":{},"children":[{"type":"text","value":"If you cannot directly import your project into your IDE, you may be able to generate IDE metadata by using a build plugin. Maven includes plugins for ","position":{"start":{"line":13,"column":1,"offset":985},"end":{"line":13,"column":152,"offset":1136}}},{"type":"element","tagName":"a","properties":{"href":"https://maven.apache.org/plugins/maven-eclipse-plugin/"},"children":[{"type":"text","value":"Eclipse","position":{"start":{"line":13,"column":153,"offset":1137},"end":{"line":13,"column":160,"offset":1144}}}],"position":{"start":{"line":13,"column":152,"offset":1136},"end":{"line":13,"column":217,"offset":1201}}},{"type":"text","value":" and ","position":{"start":{"line":13,"column":217,"offset":1201},"end":{"line":13,"column":222,"offset":1206}}},{"type":"element","tagName":"a","properties":{"href":"https://maven.apache.org/plugins/maven-idea-plugin/"},"children":[{"type":"text","value":"IDEA","position":{"start":{"line":13,"column":223,"offset":1207},"end":{"line":13,"column":227,"offset":1211}}}],"position":{"start":{"line":13,"column":222,"offset":1206},"end":{"line":13,"column":281,"offset":1265}}},{"type":"text","value":". Gradle offers plugins for ","position":{"start":{"line":13,"column":281,"offset":1265},"end":{"line":13,"column":309,"offset":1293}}},{"type":"element","tagName":"a","properties":{"href":"https://docs.gradle.org/4.2.1/userguide/userguide.html"},"children":[{"type":"text","value":"various IDEs","position":{"start":{"line":13,"column":310,"offset":1294},"end":{"line":13,"column":322,"offset":1306}}}],"position":{"start":{"line":13,"column":309,"offset":1293},"end":{"line":13,"column":379,"offset":1363}}},{"type":"text","value":".","position":{"start":{"line":13,"column":379,"offset":1363},"end":{"line":13,"column":380,"offset":1364}}}],"position":{"start":{"line":13,"column":1,"offset":985},"end":{"line":13,"column":380,"offset":1364}}},{"type":"text","value":"\n"},{"type":"element","tagName":"table","properties":{},"children":[{"type":"text","value":"\n"},{"type":"element","tagName":"thead","properties":{},"children":[{"type":"text","value":"\n"},{"type":"element","tagName":"tr","properties":{},"children":[{"type":"text","value":"\n"},{"type":"element","tagName":"th","properties":{"align":null},"children":[{"type":"element","tagName":"img","properties":{"src":"https://docs.spring.io/spring-boot/docs/current/reference/html/images/tip.png","alt":"[Tip]"},"children":[],"position":{"start":{"line":15,"column":3,"offset":1368},"end":{"line":15,"column":90,"offset":1455}}}],"position":{"start":{"line":15,"column":3,"offset":1368},"end":{"line":15,"column":90,"offset":1455}}},{"type":"text","value":"\n"}],"position":{"start":{"line":15,"column":1,"offset":1366},"end":{"line":15,"column":92,"offset":1457}}},{"type":"text","value":"\n"}],"position":{"start":{"line":15,"column":1,"offset":1366},"end":{"line":15,"column":92,"offset":1457}}},{"type":"text","value":"\n"},{"type":"element","tagName":"tbody","properties":{},"children":[{"type":"text","value":"\n"},{"type":"element","tagName":"tr","properties":{},"children":[{"type":"text","value":"\n"},{"type":"element","tagName":"td","properties":{"align":null},"children":[{"type":"text","value":"If you accidentally run a web application twice, you see a “Port already in use” error. STS users can use the ","position":{"start":{"line":17,"column":3,"offset":1525},"end":{"line":17,"column":113,"offset":1635}}},{"type":"raw","value":"<code class=\"language-text\">Relaunch</code>","position":{"start":{"line":17,"column":113,"offset":1635},"end":{"line":17,"column":123,"offset":1645}}},{"type":"text","value":" button rather than the ","position":{"start":{"line":17,"column":123,"offset":1645},"end":{"line":17,"column":147,"offset":1669}}},{"type":"raw","value":"<code class=\"language-text\">Run</code>","position":{"start":{"line":17,"column":147,"offset":1669},"end":{"line":17,"column":152,"offset":1674}}},{"type":"text","value":" button to ensure that any existing instance is closed.","position":{"start":{"line":17,"column":152,"offset":1674},"end":{"line":17,"column":207,"offset":1729}}}],"position":{"start":{"line":17,"column":3,"offset":1525},"end":{"line":17,"column":207,"offset":1729}}},{"type":"text","value":"\n"}],"position":{"start":{"line":17,"column":1,"offset":1523},"end":{"line":17,"column":209,"offset":1731}}},{"type":"text","value":"\n"}],"position":{"start":{"line":17,"column":1,"offset":1523},"end":{"line":17,"column":209,"offset":1731}}},{"type":"text","value":"\n"}],"position":{"start":{"line":15,"column":1,"offset":1366},"end":{"line":17,"column":209,"offset":1731}}},{"type":"text","value":"\n"},{"type":"element","tagName":"h2","properties":{},"children":[{"type":"text","value":"19.2 Running as a Packaged Application","position":{"start":{"line":19,"column":4,"offset":1736},"end":{"line":19,"column":42,"offset":1774}}}],"position":{"start":{"line":19,"column":1,"offset":1733},"end":{"line":19,"column":42,"offset":1774}}},{"type":"text","value":"\n"},{"type":"element","tagName":"p","properties":{},"children":[{"type":"text","value":"If you use the Spring Boot Maven or Gradle plugins to create an executable jar, you can run your application using ","position":{"start":{"line":21,"column":1,"offset":1776},"end":{"line":21,"column":116,"offset":1891}}},{"type":"raw","value":"<code class=\"language-text\">java -jar</code>","position":{"start":{"line":21,"column":116,"offset":1891},"end":{"line":21,"column":127,"offset":1902}}},{"type":"text","value":", as shown in the following example:","position":{"start":{"line":21,"column":127,"offset":1902},"end":{"line":21,"column":163,"offset":1938}}}],"position":{"start":{"line":21,"column":1,"offset":1776},"end":{"line":21,"column":163,"offset":1938}}},{"type":"text","value":"\n"},{"type":"raw","value":"<div class=\"gatsby-highlight\" data-language=\"text\"><pre class=\"language-text\"><code class=\"language-text\">$ java -jar target/myapplication-0.0.1-SNAPSHOT.jar</code></pre></div>","position":{"start":{"line":23,"column":1,"offset":1940},"end":{"line":25,"column":4,"offset":1999}}},{"type":"text","value":"\n"},{"type":"element","tagName":"p","properties":{},"children":[{"type":"text","value":"It is also possible to run a packaged application with remote debugging support enabled. Doing so lets you attach a debugger to your packaged application, as shown in the following example:","position":{"start":{"line":27,"column":1,"offset":2001},"end":{"line":27,"column":190,"offset":2190}}}],"position":{"start":{"line":27,"column":1,"offset":2001},"end":{"line":27,"column":190,"offset":2190}}},{"type":"text","value":"\n"},{"type":"raw","value":"<div class=\"gatsby-highlight\" data-language=\"text\"><pre class=\"language-text\"><code class=\"language-text\">$ java -Xdebug -Xrunjdwp:server=y,transport=dt_socket,address=8000,suspend=n \\\n       -jar target/myapplication-0.0.1-SNAPSHOT.jar</code></pre></div>","position":{"start":{"line":29,"column":1,"offset":2192},"end":{"line":32,"column":4,"offset":2330}}},{"type":"text","value":"\n"},{"type":"element","tagName":"h2","properties":{},"children":[{"type":"text","value":"19.3 Using the Maven Plugin","position":{"start":{"line":34,"column":4,"offset":2335},"end":{"line":34,"column":31,"offset":2362}}}],"position":{"start":{"line":34,"column":1,"offset":2332},"end":{"line":34,"column":31,"offset":2362}}},{"type":"text","value":"\n"},{"type":"element","tagName":"p","properties":{},"children":[{"type":"text","value":"The Spring Boot Maven plugin includes a ","position":{"start":{"line":36,"column":1,"offset":2364},"end":{"line":36,"column":41,"offset":2404}}},{"type":"raw","value":"<code class=\"language-text\">run</code>","position":{"start":{"line":36,"column":41,"offset":2404},"end":{"line":36,"column":46,"offset":2409}}},{"type":"text","value":" goal that can be used to quickly compile and run your application. Applications run in an exploded form, as they do in your IDE. The following example shows a typical Maven command to run a Spring Boot application:","position":{"start":{"line":36,"column":46,"offset":2409},"end":{"line":36,"column":261,"offset":2624}}}],"position":{"start":{"line":36,"column":1,"offset":2364},"end":{"line":36,"column":261,"offset":2624}}},{"type":"text","value":"\n"},{"type":"raw","value":"<div class=\"gatsby-highlight\" data-language=\"text\"><pre class=\"language-text\"><code class=\"language-text\">$ mvn spring-boot:run</code></pre></div>","position":{"start":{"line":38,"column":1,"offset":2626},"end":{"line":40,"column":4,"offset":2655}}},{"type":"text","value":"\n"},{"type":"element","tagName":"p","properties":{},"children":[{"type":"text","value":"You might also want to use the ","position":{"start":{"line":42,"column":1,"offset":2657},"end":{"line":42,"column":32,"offset":2688}}},{"type":"raw","value":"<code class=\"language-text\">MAVEN_OPTS</code>","position":{"start":{"line":42,"column":32,"offset":2688},"end":{"line":42,"column":44,"offset":2700}}},{"type":"text","value":" operating system environment variable, as shown in the following example:","position":{"start":{"line":42,"column":44,"offset":2700},"end":{"line":42,"column":118,"offset":2774}}}],"position":{"start":{"line":42,"column":1,"offset":2657},"end":{"line":42,"column":118,"offset":2774}}},{"type":"text","value":"\n"},{"type":"raw","value":"<div class=\"gatsby-highlight\" data-language=\"text\"><pre class=\"language-text\"><code class=\"language-text\">$ export MAVEN_OPTS=-Xmx1024m</code></pre></div>","position":{"start":{"line":44,"column":1,"offset":2776},"end":{"line":46,"column":4,"offset":2813}}},{"type":"text","value":"\n"},{"type":"element","tagName":"h2","properties":{},"children":[{"type":"text","value":"19.4 Using the Gradle Plugin","position":{"start":{"line":48,"column":4,"offset":2818},"end":{"line":48,"column":32,"offset":2846}}}],"position":{"start":{"line":48,"column":1,"offset":2815},"end":{"line":48,"column":32,"offset":2846}}},{"type":"text","value":"\n"},{"type":"element","tagName":"p","properties":{},"children":[{"type":"text","value":"The Spring Boot Gradle plugin also includes a ","position":{"start":{"line":50,"column":1,"offset":2848},"end":{"line":50,"column":47,"offset":2894}}},{"type":"raw","value":"<code class=\"language-text\">bootRun</code>","position":{"start":{"line":50,"column":47,"offset":2894},"end":{"line":50,"column":56,"offset":2903}}},{"type":"text","value":" task that can be used to run your application in an exploded form. The ","position":{"start":{"line":50,"column":56,"offset":2903},"end":{"line":50,"column":128,"offset":2975}}},{"type":"raw","value":"<code class=\"language-text\">bootRun</code>","position":{"start":{"line":50,"column":128,"offset":2975},"end":{"line":50,"column":137,"offset":2984}}},{"type":"text","value":" task is added whenever you apply the ","position":{"start":{"line":50,"column":137,"offset":2984},"end":{"line":50,"column":175,"offset":3022}}},{"type":"raw","value":"<code class=\"language-text\">org.springframework.boot</code>","position":{"start":{"line":50,"column":175,"offset":3022},"end":{"line":50,"column":201,"offset":3048}}},{"type":"text","value":" and ","position":{"start":{"line":50,"column":201,"offset":3048},"end":{"line":50,"column":206,"offset":3053}}},{"type":"raw","value":"<code class=\"language-text\">java</code>","position":{"start":{"line":50,"column":206,"offset":3053},"end":{"line":50,"column":212,"offset":3059}}},{"type":"text","value":" plugins and is shown in the following example:","position":{"start":{"line":50,"column":212,"offset":3059},"end":{"line":50,"column":259,"offset":3106}}}],"position":{"start":{"line":50,"column":1,"offset":2848},"end":{"line":50,"column":259,"offset":3106}}},{"type":"text","value":"\n"},{"type":"raw","value":"<div class=\"gatsby-highlight\" data-language=\"text\"><pre class=\"language-text\"><code class=\"language-text\">$ gradle bootRun</code></pre></div>","position":{"start":{"line":52,"column":1,"offset":3108},"end":{"line":54,"column":4,"offset":3132}}},{"type":"text","value":"\n"},{"type":"element","tagName":"p","properties":{},"children":[{"type":"text","value":"You might also want to use the ","position":{"start":{"line":56,"column":1,"offset":3134},"end":{"line":56,"column":32,"offset":3165}}},{"type":"raw","value":"<code class=\"language-text\">JAVA_OPTS</code>","position":{"start":{"line":56,"column":32,"offset":3165},"end":{"line":56,"column":43,"offset":3176}}},{"type":"text","value":" operating system environment variable, as shown in the following example:","position":{"start":{"line":56,"column":43,"offset":3176},"end":{"line":56,"column":117,"offset":3250}}}],"position":{"start":{"line":56,"column":1,"offset":3134},"end":{"line":56,"column":117,"offset":3250}}},{"type":"text","value":"\n"},{"type":"raw","value":"<div class=\"gatsby-highlight\" data-language=\"text\"><pre class=\"language-text\"><code class=\"language-text\">$ export JAVA_OPTS=-Xmx1024m</code></pre></div>","position":{"start":{"line":58,"column":1,"offset":3252},"end":{"line":60,"column":4,"offset":3288}}},{"type":"text","value":"\n"},{"type":"element","tagName":"h2","properties":{},"children":[{"type":"text","value":"19.5 Hot Swapping","position":{"start":{"line":62,"column":4,"offset":3293},"end":{"line":62,"column":21,"offset":3310}}}],"position":{"start":{"line":62,"column":1,"offset":3290},"end":{"line":62,"column":21,"offset":3310}}},{"type":"text","value":"\n"},{"type":"element","tagName":"p","properties":{},"children":[{"type":"text","value":"Since Spring Boot applications are just plain Java applications, JVM hot-swapping should work out of the box. JVM hot swapping is somewhat limited with the bytecode that it can replace. For a more complete solution, ","position":{"start":{"line":64,"column":1,"offset":3312},"end":{"line":64,"column":217,"offset":3528}}},{"type":"element","tagName":"a","properties":{"href":"https://zeroturnaround.com/software/jrebel/"},"children":[{"type":"text","value":"JRebel","position":{"start":{"line":64,"column":218,"offset":3529},"end":{"line":64,"column":224,"offset":3535}}}],"position":{"start":{"line":64,"column":217,"offset":3528},"end":{"line":64,"column":270,"offset":3581}}},{"type":"text","value":" can be used.","position":{"start":{"line":64,"column":270,"offset":3581},"end":{"line":64,"column":283,"offset":3594}}}],"position":{"start":{"line":64,"column":1,"offset":3312},"end":{"line":64,"column":283,"offset":3594}}},{"type":"text","value":"\n"},{"type":"element","tagName":"p","properties":{},"children":[{"type":"text","value":"The ","position":{"start":{"line":66,"column":1,"offset":3596},"end":{"line":66,"column":5,"offset":3600}}},{"type":"raw","value":"<code class=\"language-text\">spring-boot-devtools</code>","position":{"start":{"line":66,"column":5,"offset":3600},"end":{"line":66,"column":27,"offset":3622}}},{"type":"text","value":" module also includes support for quick application restarts. See the ","position":{"start":{"line":66,"column":27,"offset":3622},"end":{"line":66,"column":97,"offset":3692}}},{"type":"element","tagName":"a","properties":{"href":"https://docs.spring.io/spring-boot/docs/current/reference/html/using-boot-devtools.html"},"children":[{"type":"text","value":"Chapter 20, ","position":{"start":{"line":66,"column":98,"offset":3693},"end":{"line":66,"column":110,"offset":3705}}},{"type":"element","tagName":"em","properties":{},"children":[{"type":"text","value":"Developer Tools","position":{"start":{"line":66,"column":111,"offset":3706},"end":{"line":66,"column":126,"offset":3721}}}],"position":{"start":{"line":66,"column":110,"offset":3705},"end":{"line":66,"column":127,"offset":3722}}}],"position":{"start":{"line":66,"column":97,"offset":3692},"end":{"line":66,"column":217,"offset":3812}}},{"type":"text","value":" section later in this chapter and the ","position":{"start":{"line":66,"column":217,"offset":3812},"end":{"line":66,"column":256,"offset":3851}}},{"type":"element","tagName":"a","properties":{"href":"https://docs.spring.io/spring-boot/docs/current/reference/html/howto-hotswapping.html"},"children":[{"type":"text","value":"Hot swapping “How-to”","position":{"start":{"line":66,"column":257,"offset":3852},"end":{"line":66,"column":278,"offset":3873}}}],"position":{"start":{"line":66,"column":256,"offset":3851},"end":{"line":66,"column":366,"offset":3961}}},{"type":"text","value":" for details.","position":{"start":{"line":66,"column":366,"offset":3961},"end":{"line":66,"column":379,"offset":3974}}}],"position":{"start":{"line":66,"column":1,"offset":3596},"end":{"line":66,"column":379,"offset":3974}}},{"type":"text","value":"\n"},{"type":"element","tagName":"hr","properties":{},"children":[],"position":{"start":{"line":68,"column":1,"offset":3976},"end":{"line":68,"column":7,"offset":3982}}}],"position":{"start":{"line":1,"column":1,"offset":0},"end":{"line":68,"column":7,"offset":3982}}}}